<wordSearch id='11' hideWords='false' heading='Can you find all 20 EUROPEAN COUNTRIES hidden in the grid?'>
	<row id='0'>GAADNMGTIIIPTTRE</row>
	<row id='1'>RUINOADEEMHTTTOS</row>
	<row id='2'>ESTARLYORUAEAEII</row>
	<row id='3'>ETALWTDENMARKLCE</row>
	<row id='4'>CROEAAUGSAAHIEYR</row>
	<row id='5'>EIRRYFAPARONLLTE</row>
	<row id='6'>PACIERAAEHBAYUSC</row>
	<row id='7'>SOTSYIPOLANDASEN</row>
	<row id='8'>EWRONTMDTDEIIEAA</row>
	<row id='9'>YCETRFSTDUSNLFIR</row>
	<row id='10'>TOEDUNHTTNCORTRF</row>
	<row id='11'>ANTWEGDNALNIFEAC</row>
	<row id='12'>UWTECNADTEIATCGI</row>
	<row id='13'>TEIAOSILNNEUTHLN</row>
	<row id='14'>UNITEDKINGDOMCUH</row>
	<row id='15'>MUIGLEBAHEIEOABO</row>
	<word>AUSTRIA</word>
	<word>BELGIUM</word>
	<word>BULGARIA</word>
	<word>CROATIA</word>
	<word>DENMARK</word>
	<word>FINLAND</word>
	<word>FRANCE</word>
	<word>GERMANY</word>
	<word>GREECE</word>
	<word>HUNGARY</word>
	<word>ICELAND</word>
	<word>IRELAND</word>
	<word>ITALY</word>
	<word>MALTA</word>
	<word>NORWAY</word>
	<word>POLAND</word>
	<word>PORTUGAL</word>
	<word>SPAIN</word>
	<word>SWEDEN</word>
	<word>UNITED KINGDOM</word>
</wordSearch>



















