<wordSearch id='66' hideWords='false' heading='Can you find all 20 PLUMBING words in the grid?'>

<row id='0'>GTUNPICUTSSFWDST</row>
<row id='1'>SGNITTIFEREEHLOR</row>
<row id='2'>CCPFEISSCETVOIET</row>
<row id='3'>UELUITEHUIEOLHDU</row>
<row id='4'>STUCMOUWALTESART</row>
<row id='5'>HTGGSPTTFPTATEVG</row>
<row id='6'>GRRCAQIUAIWGTYRG</row>
<row id='7'>ENEBUTHTABUASPAT</row>
<row id='8'>INIWNYSGBOWEREIE</row>
<row id='9'>TOCPOTSIIIFOLOOD</row>
<row id='10'>AENCPHTMNAEALGWR</row>
<row id='11'>YCHUOISDTKTWURAA</row>
<row id='12'>RTORNEREKLNOENRI</row>
<row id='13'>LEAKINGDREGNULPN</row>
<row id='14'>RRPDAEERMOCREEDA</row>
<row id='15'>SIVTIAINIHLEIPRR</row>


<word>BATHTUB</word>
<word>DRAIN</word>
<word>DRIPPING</word>
<word>FAUCET</word>
<word>FITTINGS</word>
<word>LEAKING</word>
<word>PIPES</word>
<word>PLIERS</word>
<word>PLUG</word>
<word>PLUNGER</word>
<word>PUMP</word>
<word>SHOWER</word>
<word>SINK</word>
<word>TAPS</word>
<word>TOILET</word>
<word>TOOLS</word>
<word>VALVE</word>
<word>WASHER</word>
<word>WATER</word>
<word>WRENCH</word>


</wordSearch>


